cratis_admin_suit
