Metadata-Version: 1.0
Name: django-cratis-suit
Version: 0.1.2
Summary: Django-suit integration
Home-page: UNKNOWN
Author: Alex Rudakov
Author-email: ribozz@gmail.com
License: MIT License
Platform: UNKNOWN
